sdenv.py
pysdenv-1.0.0.dist-info/METADATA
pysdenv-1.0.0.dist-info/WHEEL
pysdenv-1.0.0.dist-info/top_level.txt
pysdenv-1.0.0.dist-info/RECORD
