Metadata-Version: 2.4
Name: pysdenv
Version: 1.0.0
Summary: Python wrapper for sdenv - 瑞数VMP补环境框架
Requires-Python: >=3.7
Dynamic: requires-python
Dynamic: summary
